odoo/addons/l10n_ro_partner_create_by_vat/README.rst
odoo/addons/l10n_ro_partner_create_by_vat/__init__.py
odoo/addons/l10n_ro_partner_create_by_vat/__manifest__.py
odoo/addons/l10n_ro_partner_create_by_vat/i18n/l10n_ro_partner_create_by_vat.pot
odoo/addons/l10n_ro_partner_create_by_vat/i18n/ro.po
odoo/addons/l10n_ro_partner_create_by_vat/i18n/ro_RO.po
odoo/addons/l10n_ro_partner_create_by_vat/models/__init__.py
odoo/addons/l10n_ro_partner_create_by_vat/models/res_partner.py
odoo/addons/l10n_ro_partner_create_by_vat/readme/CONTRIBUTORS.rst
odoo/addons/l10n_ro_partner_create_by_vat/readme/DESCRIPTION.rst
odoo/addons/l10n_ro_partner_create_by_vat/readme/INSTALL.rst
odoo/addons/l10n_ro_partner_create_by_vat/readme/USAGE.rst
odoo/addons/l10n_ro_partner_create_by_vat/static/description/icon.png
odoo/addons/l10n_ro_partner_create_by_vat/static/description/index.html
odoo/addons/l10n_ro_partner_create_by_vat/tests/__init__.py
odoo/addons/l10n_ro_partner_create_by_vat/tests/test_create_partner_by_vat.py
odoo13_addon_l10n_ro_partner_create_by_vat-13.0.3.0.1.dist-info/METADATA
odoo13_addon_l10n_ro_partner_create_by_vat-13.0.3.0.1.dist-info/WHEEL
odoo13_addon_l10n_ro_partner_create_by_vat-13.0.3.0.1.dist-info/top_level.txt
odoo13_addon_l10n_ro_partner_create_by_vat-13.0.3.0.1.dist-info/RECORD
